easystate
