Metadata-Version: 1.1
Name: easystate
Version: 0.3
Summary: Python State-Machine library
Home-page: https://github.com/pylover/easystate
Author: Vahid Mardani
Author-email: vahid.mardani@gmail.com
License: UNKNOWN
Platform: any
Classifier: Development Status :: 5 - Production/Stable
Classifier: License :: Freeware
Classifier: Intended Audience :: Developers
Classifier: Operating System :: OS Independent
Classifier: Programming Language :: Python :: 2.6
Classifier: Programming Language :: Python :: 2.7
Classifier: Topic :: Software Development :: Libraries
